{
  "nick": "Slemgrim",
  "name": "Markus Ritberger",
  "email": "contact@slemgrim.com",
  "about": "Slemgrim.com is the professional blog of Markus Ritberger where he writes about programming, software development, and architecture focused on the web. He's a language agnostic programmer living in Linz, Austria",
  "hire": "Currently i work as lead developer at karriere.at but you can <a href='/hire'>hire</a> me as freelancer",
  "image": "/images/slemgrim.jpg",
  "social": [
    {
      "name": "Github",
      "uri": "https://github.com/Slemgrim"
    },
    {
      "name": "Twitter",
      "uri": "https://twitter.com/slemgrim"
    }
  ]
}